imio.media-0.2.11-py2.7-nspkg.pth
imio/media/__init__.py
imio/media/configure.zcml
imio/media/endpoints.py
imio/media/imio_media.py
imio/media/interfaces.py
imio/media/setuphandlers.py
imio/media/testing.py
imio/media/testing.zcml
imio/media/browser/__init__.py
imio/media/browser/collection_oembed_view.py
imio/media/browser/configure.zcml
imio/media/browser/consumer.py
imio/media/browser/faceted_oembed_view.py
imio/media/browser/medialink_oembed_view.py
imio/media/browser/provider.py
imio/media/browser/utils.py
imio/media/browser/static/.gitkeep
imio/media/browser/static/imio-media.css
imio/media/browser/static/video-icon.png
imio/media/browser/templates/collection_oembed_view.pt
imio/media/browser/templates/list-oembed.pt
imio/media/browser/templates/list-oembeds.pt
imio/media/browser/templates/medialink_oembed_view.pt
imio/media/locales/imio.media.pot
imio/media/portlets/__init__.py
imio/media/portlets/configure.zcml
imio/media/portlets/media.pt
imio/media/portlets/media.py
imio/media/profiles/default/browserlayer.xml
imio/media/profiles/default/cssregistry.xml
imio/media/profiles/default/metadata.xml
imio/media/profiles/default/portlets.xml
imio/media/profiles/default/types.xml
imio/media/profiles/default/types/Collection.xml
imio/media/profiles/default/types/media_link.xml
imio/media/profiles/testing/imio.media.txt
imio/media/profiles/testing/metadata.xml
imio/media/profiles/testing/properties.xml
imio/media/tests/__init__.py
imio/media/tests/example.robot
imio/media/tests/test_endpoints.py
imio/media/tests/test_product.py
imio/media/tests/test_robot.py
imio.media-0.2.11.dist-info/DESCRIPTION.rst
imio.media-0.2.11.dist-info/METADATA
imio.media-0.2.11.dist-info/RECORD
imio.media-0.2.11.dist-info/WHEEL
imio.media-0.2.11.dist-info/entry_points.txt
imio.media-0.2.11.dist-info/metadata.json
imio.media-0.2.11.dist-info/namespace_packages.txt
imio.media-0.2.11.dist-info/top_level.txt
