Metadata-Version: 2.0
Name: imio.media
Version: 0.2.11
Summary: This package is used to view video from links. You can add video or photo from a link which accept oembeded protocol. This package has as dependecy collective.oembeded.
Home-page: http://pypi.python.org/pypi/imio.media
Author: Benoît Suttor
Author-email: benoit.suttor@imio.be
License: BSD
Keywords: Plone Python
Platform: UNKNOWN
Classifier: Framework :: Plone
Classifier: Programming Language :: Python
Provides-Extra: test
Requires-Dist: Plone
Requires-Dist: setuptools
Requires-Dist: collective.oembed
Requires-Dist: plone.app.dexterity
Requires-Dist: plone.app.contenttypes
Requires-Dist: plone.api
Requires-Dist: eea.facetednavigation
Provides-Extra: test
Requires-Dist: plone.app.robotframework; extra == 'test'
Requires-Dist: ipdb; extra == 'test'
